d8n/__init__.py
d8n/d8nClient.py
d8n-0.4.0.dist-info/METADATA
d8n-0.4.0.dist-info/WHEEL
d8n-0.4.0.dist-info/top_level.txt
d8n-0.4.0.dist-info/RECORD
