Metadata-Version: 2.2
Name: d8n
Version: 0.4.0
Summary: d8n API python library
Author: Christo
Author-email: christochristov@duck.com
Classifier: Programming Language :: Python :: 3
Classifier: License :: OSI Approved :: MIT License
Classifier: Operating System :: OS Independent
Requires-Python: >=3.6
Dynamic: author
Dynamic: author-email
Dynamic: classifier
Dynamic: requires-python
Dynamic: summary
